nachopy/__init__.py
nachopy-0.1.dist-info/METADATA
nachopy-0.1.dist-info/WHEEL
nachopy-0.1.dist-info/top_level.txt
nachopy-0.1.dist-info/RECORD
