Metadata-Version: 2.1
Name: nachopy
Version: 0.1
Summary: Nachoooooooooooooooooooooooooooo!!
Home-page: https://github.com/chrislauyc/nachopy.git
Author: Chris Lau
Author-email: chrislyc.lau@gmail.com
License: UNKNOWN
Platform: UNKNOWN
